beautifuldiscord/__init__.py
beautifuldiscord/__main__.py
beautifuldiscord/app.py
beautifuldiscord/asar.py
beaudis-0.2.0.dist-info/LICENSE
beaudis-0.2.0.dist-info/METADATA
beaudis-0.2.0.dist-info/WHEEL
beaudis-0.2.0.dist-info/entry_points.txt
beaudis-0.2.0.dist-info/top_level.txt
beaudis-0.2.0.dist-info/RECORD
