Metadata-Version: 2.1
Name: beaudis
Version: 0.2.0
Summary: Adds custom CSS support to Discord.
Home-page: https://github.com/leovoel/BeautifulDiscord
Author: leovoel
License: MIT
Platform: UNKNOWN
License-File: LICENSE
Requires-Dist: psutil
